pglet/__init__.py
pglet/barchart.py
pglet/button.py
pglet/callout.py
pglet/checkbox.py
pglet/choicegroup.py
pglet/combobox.py
pglet/connection.py
pglet/constants.py
pglet/control.py
pglet/control_event.py
pglet/datepicker.py
pglet/dialog.py
pglet/dropdown.py
pglet/event.py
pglet/form.py
pglet/grid.py
pglet/html.py
pglet/icon.py
pglet/iframe.py
pglet/image.py
pglet/linechart.py
pglet/link.py
pglet/message.py
pglet/nav.py
pglet/page.py
pglet/panel.py
pglet/persona.py
pglet/pglet.py
pglet/piechart.py
pglet/progress.py
pglet/protocol.py
pglet/reconnecting_websocket.py
pglet/ref.py
pglet/searchbox.py
pglet/slider.py
pglet/spinbutton.py
pglet/spinner.py
pglet/splitstack.py
pglet/stack.py
pglet/tabs.py
pglet/text.py
pglet/textbox.py
pglet/toggle.py
pglet/toolbar.py
pglet/utils.py
pglet/verticalbarchart.py
pglet-0.7.3.dist-info/WHEEL
pglet-0.7.3.dist-info/METADATA
pglet-0.7.3.dist-info/license_files/LICENSE
pglet-0.7.3.dist-info/RECORD
