Metadata-Version: 2.1
Name: pglet
Version: 0.7.3
Summary: Pglet client for Python - easily build interactive web apps in Python
License: MIT
Author-email: Appveyor Systems Inc. <hello@pglet.io>
Requires-Python: >=3.7
Classifier: License :: OSI Approved :: MIT License
Classifier: Operating System :: OS Independent
Classifier: Programming Language :: Python :: 3
Classifier: Programming Language :: Python :: 3.7
Classifier: Programming Language :: Python :: 3.8
Requires-Dist: beartype>=0.9.1
Requires-Dist: typing_extensions; python_version < "3.8"
Requires-Dist: websocket-client>=1.2.1
Project-URL: documentation, https://pglet.io/docs/
Project-URL: repository, https://github.com/pglet/pglet-python
